mlmtools/__init__.py
mlmtools/admin.py
mlmtools/apps.py
mlmtools/forms.py
mlmtools/models.py
mlmtools/tests.py
mlmtools/urls.py
mlmtools/views.py
mlmtools/migrations/0001_initial.py
mlmtools/migrations/0002_marketernode.py
mlmtools/migrations/0003_auto_20210219_0836.py
mlmtools/migrations/0004_auto_20210219_1343.py
mlmtools/migrations/0005_marketernode_node_cut.py
mlmtools/migrations/0006_auto_20210219_1421.py
mlmtools/migrations/0007_auto_20210219_1440.py
mlmtools/migrations/0008_auto_20210220_1744.py
mlmtools/migrations/0009_auto_20210305_1743.py
mlmtools/migrations/0010_dummytarget.py
mlmtools/migrations/0011_alter_dummytarget_amount.py
mlmtools/migrations/0012_alter_codeuse_amount.py
mlmtools/migrations/0013_auto_20220902_1228.py
mlmtools/migrations/__init__.py
mlmtools/templates/admin/mlmtools/marketernode/change_form.html
mlmtools/templates/floppyforms/range.html
mlmtools/templates/mlmtools/code_detail.html
mlmtools/templates/mlmtools/list_codes.html
mlmtools/templates/mlmtools/node_detail.html
mlmtools/templates/mlmtools/tester.html
mlmprovisions-0.1.8.dist-info/LICENCE
mlmprovisions-0.1.8.dist-info/METADATA
mlmprovisions-0.1.8.dist-info/WHEEL
mlmprovisions-0.1.8.dist-info/top_level.txt
mlmprovisions-0.1.8.dist-info/RECORD
