Metadata-Version: 2.1
Name: mlmprovisions
Version: 0.1.8
Summary: Reusable Django app to track provisions for affiliate partners. Includes tools for multi-level marketing provisions.
Home-page: https://github.com/belda/mlmprovisions
Author: Belda
Author-email: jakub.belescak@centrum.cz
Classifier: Programming Language :: Python :: 3
Classifier: License :: OSI Approved :: MIT License
Classifier: Operating System :: OS Independent
Requires-Python: >=3.4
License-File: LICENCE
Requires-Dist: django
Requires-Dist: django-floppyforms
Requires-Dist: django-treenode
